verilog/por_dig.v
module por_dig(
//INPUTS
input logic [2:0] otrip,
input logic force_pdn,
input logic force_rc_osc,
input logic force_short_oneshot,
input logic pwup_filt,
input logic osc_ck,
//OUTPUTS
output osc_ena,
output logic [7:0] otrip_decoded,
output force_pdnb,
output por_unbuf,
//DEBUG OUTPUTS
output logic osc_ck_256,
output startup_timed_out,
output por_timed_out
);

  assign force_pdnb = ~force_pdn;
  assign osc_ena = force_rc_osc | (pwup_filt & ~por_timed_out);

  //TRIP-VOLTAGE 3-to-8 DECODER
  always @ (otrip) begin
    case(otrip)
      3'b111: otrip_decoded = 8'b10000000;
      3'b110: otrip_decoded = 8'b01000000;
      3'b101: otrip_decoded = 8'b00100000;
      3'b100: otrip_decoded = 8'b00010000;
      3'b011: otrip_decoded = 8'b00001000;
      3'b010: otrip_decoded = 8'b00000100;
      3'b001: otrip_decoded = 8'b00000010;
      3'b000: otrip_decoded = 8'b00000001;
    endcase
  end

  //COUNTER RESET
  reg cnt_rsb_stg1, cnt_rsb_stg2, cnt_rsb;

  always @ (posedge osc_ck or negedge pwup_filt) begin
    if (!pwup_filt) begin
      cnt_rsb_stg1 <= 0;
      cnt_rsb_stg2 <= 0;
      cnt_rsb <= 0;
    end else begin
      cnt_rsb_stg1 <= 1;
      cnt_rsb_stg2 <= cnt_rsb_stg1;
      cnt_rsb <= cnt_rsb_stg2;
    end
  end

  //9-BIT STARTUP ONE-SHOT
  reg [8:0] cnt_st;

  assign startup_timed_out = (cnt_st == 9'b111111111);

  always @ (posedge osc_ck or negedge cnt_rsb) begin
    if (!cnt_rsb) begin
      cnt_st <= 0;
    end else begin
      cnt_st <= startup_timed_out ? cnt_st : force_short_oneshot ? (cnt_st & 9'b111100000) + 9'b000111111 : cnt_st + 1;
    end
  end

  //OUTPUT
  assign por_unbuf = startup_timed_out & (!por_timed_out);

  //15-BIT POR ONE-SHOT
  reg [14:0] cnt_por;

  assign por_timed_out = (cnt_por == 15'b111111111111111);

  always @ (posedge osc_ck or negedge cnt_rsb) begin
    if (!cnt_rsb) begin
      cnt_por <= 0;
    end else begin
      cnt_por <= por_unbuf ? force_short_oneshot ? (cnt_por & 15'b111100000000000) + 15'b000111111111111 : cnt_por + 1 : cnt_por;
    end
  end

  //DEBUG clock osc_ck/256
  reg [6:0] cnt_ck_256;

  always @ (posedge osc_ck or negedge cnt_rsb) begin
    if (!cnt_rsb) begin
      cnt_ck_256 <= 0;
      osc_ck_256 <= 0;
    end else begin
      cnt_ck_256 <= cnt_ck_256 + 1;
      osc_ck_256 <= (cnt_ck_256 == 7'b1111111) ? !osc_ck_256 : osc_ck_256;
    end
  end

endmodule

verilog/behavioral/rc_osc.v
//`timescale 1ns/100fs

module rc_osc(
input logic osc_ena,
input logic dvdd,
input logic dvss,
output logic osc_ck
);

//656kHz
always #762.2 osc_ck = osc_ena ? ~osc_ck : 0;

initial begin
  osc_ck <= 0;
end
endmodule

verilog/behavioral/comparator.v
module comparator(
input real avdd,
input logic avss,
input logic dvdd,
input logic dvss,
input real vinp,
input real vinn,
input logic ena,
input real ibias,
output dout
);

assign dout = ena & (ibias > 200e-9) ? (vinp > vinn) ? 1 : 0 : 0;

endmodule

verilog/behavioral/ibias_gen.v
module ibias_gen(
input real avdd,
input logic avss,
input logic dvdd,
input logic dvss,
input logic ena,
input logic isrc_sel,
input real ibg_200n,
output real ibias,
output real itest
);

assign ibias = ena ? isrc_sel ? 800e-9 : 700e-9 : 0;

endmodule

verilog/behavioral/rstring_mux.v
module rstring_mux(
//INPUT
input real avdd,
input logic avss,
input logic dvdd,
input logic dvss,
input logic ena,
input logic [7:0] otrip_decoded,
//OUTPUTS
output real vin
);

`define UNIT_R 50e3

real vtrip_7;
real vtrip_6;
real vtrip_5;
real vtrip_4;
real vtrip_3;
real vtrip_2;
real vtrip_1;
real vtrip_0;

assign vtrip_0 = ena ? avdd * (`UNIT_R*7 + `UNIT_R*28) / (`UNIT_R*70) : 0;
assign vtrip_1 = ena ? avdd * (`UNIT_R*6 + `UNIT_R*28) / (`UNIT_R*70) : 0;
assign vtrip_2 = ena ? avdd * (`UNIT_R*5 + `UNIT_R*28) / (`UNIT_R*70) : 0;
assign vtrip_3 = ena ? avdd * (`UNIT_R*4 + `UNIT_R*28) / (`UNIT_R*70) : 0;
assign vtrip_4 = ena ? avdd * (`UNIT_R*3 + `UNIT_R*28) / (`UNIT_R*70) : 0;
assign vtrip_5 = ena ? avdd * (`UNIT_R*2 + `UNIT_R*28) / (`UNIT_R*70) : 0;
assign vtrip_6 = ena ? avdd * (`UNIT_R*1 + `UNIT_R*28) / (`UNIT_R*70) : 0;
assign vtrip_7 = ena ? avdd * (`UNIT_R*0 + `UNIT_R*28) / (`UNIT_R*70) : 0;

  always @ (vtrip_7, vtrip_6, vtrip_5, vtrip_4, vtrip_3, vtrip_2, vtrip_1, vtrip_0, otrip_decoded) begin
    case (otrip_decoded)
      8'b10000000: vin = vtrip_7;
      8'b01000000: vin = vtrip_6;
      8'b00100000: vin = vtrip_5;
      8'b00010000: vin = vtrip_4;
      8'b00001000: vin = vtrip_3;
      8'b00000100: vin = vtrip_2;
      8'b00000010: vin = vtrip_1;
      8'b00000001: vin = vtrip_0;
      default: vin <= 0;
    endcase
  end

endmodule

verilog/por_ana.v
module por_ana(
//INPUTS
input real avdd,
input logic avss,
input logic dvdd,
input logic dvss,
input logic [7:0] otrip_decoded,
input real vbg_1v2,
input logic force_pdnb,
input logic isrc_sel,
input real ibg_200n,
input logic osc_ena,
input logic por_unbuf,
//OUTPUTS
output pwup_filt,
output osc_ck,
output logic por,
output logic porb,
output logic porb_h,
output real vin,
output real itest
);

assign por = por_unbuf; //lvls to avdd
assign porb = !por_unbuf; //lvls to avdd
assign porb_h = !por_unbuf; //lvls to avdd

rstring_mux rstring_mux(
.avdd(avdd),
.avss(avss),
.dvdd(dvdd),
.dvss(dvss),
.ena(force_pdnb),
.otrip_decoded(otrip_decoded), //lvls not modeled
.vin(vin)
);

real ibias;

ibias_gen ibias_gen(
.avdd(avdd),
.avss(avss),
.dvdd(dvdd),
.dvss(dvss),
.ena(force_pdnb),
.isrc_sel(isrc_sel),
.ibg_200n(ibg_200n),
.ibias(ibias),
.itest(itest)
);

comparator comparator(
.avdd(avdd),
.avss(avss),
.dvdd(dvdd),
.dvss(dvss),
.vinp(vin),
.vinn(vbg_1v2),
.ena(force_pdnb),
.ibias(ibias),
.dout(pwup_filt)
);

rc_osc rc_osc(
.dvdd(dvdd),
.dvss(dvss),
.osc_ena(osc_ena),
.osc_ck(osc_ck)
);

endmodule

verilog/por.v
`include "behavioral/rc_osc.v"
`include "behavioral/rstring_mux.v"
`include "behavioral/comparator.v"
`include "behavioral/ibias_gen.v"
`include "por_ana.v"
`include "por_dig.v"

module por(
//INPUTS
input real avdd,
input logic avss,
input logic dvdd,
input logic dvss,
input real vbg_1v2,
input logic [2:0] otrip, //trip voltage select
input logic force_pdn, //a 1 means power down the block
input logic force_rc_osc, //force rc oscillator on
input logic force_short_oneshot, //shorten 1ms/50ms timer for faster simulation
input logic isrc_sel, //chooses between internal bias gen (0) or external bandgap current (1)
input real ibg_200n, //bandgap current
//OUTPUTS
output porb_h, //negative logic por 3v3
output porb, //negative logic por 1v8
output por, //positive logic por 1v8
//DEBUG OUTPUTS
output osc_ck, //~656kHz, main clock
output osc_ck_256, //divided down clock for testing ~2.5kHz
output real itest, //700nA bias current
output pwup_filt, //high when avdd > trip point
output real vin, //avdd divided down voltage to compare to 1.2V bg
output startup_timed_out, //initial 1ms timer
output por_timed_out //50ms timer
);

wire [7:0] otrip_decoded;

por_ana por_ana(
//INPUTS
.avdd(avdd),
.avss(avss),
.dvdd(dvdd),
.dvss(dvss),
.otrip_decoded(otrip_decoded),
.vbg_1v2(vbg_1v2),
.force_pdnb(force_pdnb),
.isrc_sel(isrc_sel),
.ibg_200n(ibg_200n),
.osc_ena(osc_ena),
.por_unbuf(por_unbuf),
//OUTPUTS
.pwup_filt(pwup_filt),
.osc_ck(osc_ck),
.por(por),
.porb(porb),
.porb_h(porb_h),
//DEBUG OUTPUTS
.vin(vin), //input to comparator for comparing to 1.2V bg voltage
.itest(itest) //mirror of current gen 0.7uA nominal
);

por_dig por_dig(
//INPUTS
.otrip(otrip),
.force_pdn(force_pdn),
.force_rc_osc(force_rc_osc),
.force_short_oneshot(force_short_oneshot),
.pwup_filt(pwup_filt),
.osc_ck(osc_ck),
//OUTPUTS
.osc_ena(osc_ena),
.otrip_decoded(otrip_decoded),
.force_pdnb(force_pdnb),
.por_unbuf(por_unbuf),
//DEBUG OUTPUTS
.osc_ck_256(osc_ck_256),
.startup_timed_out(startup_timed_out),
.por_timed_out(por_timed_out)
);

endmodule

verilog/tb_por.v
`include "por.v"
module tb_por();

real avdd;
real vbg_1v2;
logic [2:0] otrip;
logic force_pdn;
logic force_rc_osc;
logic force_short_oneshot;
logic isrc_sel;
real ibg_200n;

por por(
//INPUTS
.avdd(avdd),
.avss(avss),
.dvdd(dvdd),
.dvss(dvss),
.vbg_1v2(vbg_1v2),
.otrip(otrip),
.force_pdn(force_pdn), //debug
.force_rc_osc(force_rc_osc), //debug
.force_short_oneshot(force_short_oneshot), //debug, fast sim
.isrc_sel(isrc_sel), //debug
.ibg_200n(ibg_200n), //debug 200nA current
//OUTPUTS
.porb_h(porb_h),
.porb(porb),
.por(por),
//DEBUG OUTPUTS
.osc_ck(osc_ck),
.osc_ck_256(osc_ck_256),
.itest(itest),
.pwup_filt(pwup_filt),
.vin(vin),
.startup_timed_out(startup_timed_out),
.por_timed_out(por_timed_out)
);

assign avss = 1'b0;
assign dvdd = 1'b1;
assign dvss = 1'b0;

initial begin
  $dumpfile("tb_por.vcd");
  $dumpvars(0,tb_por);

  //INPUTS
  avdd = 2.0;
  vbg_1v2 = 1.2;
  otrip = 3'b111;
  //DEBUG INPUTS
  force_pdn = 1'b0;
  force_rc_osc = 1'b0;
  force_short_oneshot = 1'b0;
  isrc_sel = 1'b0;
  ibg_200n = 200e-9;
  #20000000
  avdd = 3.1;
  #80000000
  avdd = 2.0;
  #40000000
  avdd = 3.1;
  #80000000
  $finish;
end


endmodule

verilog/tb_por.vcd
$date
	Thu Mar 14 08:22:36 2024
$end
$version
	Icarus Verilog
$end
$timescale
	1s
$end
$scope module tb_por $end
$var wire 1 ! avss $end
$var wire 1 " dvdd $end
$var wire 1 # dvss $end
$var wire 1 $ vin $end
$var wire 1 % startup_timed_out $end
$var wire 1 & pwup_filt $end
$var wire 1 ' porb_h $end
$var wire 1 ( porb $end
$var wire 1 ) por_timed_out $end
$var wire 1 * por $end
$var wire 1 + osc_ck_256 $end
$var wire 1 , osc_ck $end
$var wire 1 - itest $end
$var reg 1 . force_pdn $end
$var reg 1 / force_rc_osc $end
$var reg 1 0 force_short_oneshot $end
$var reg 1 1 isrc_sel $end
$var reg 3 2 otrip [2:0] $end
$var real 1 3 avdd $end
$var real 1 4 ibg_200n $end
$var real 1 5 vbg_1v2 $end
$scope module por $end
$var wire 1 ! avss $end
$var wire 1 " dvdd $end
$var wire 1 # dvss $end
$var wire 1 . force_pdn $end
$var wire 1 / force_rc_osc $end
$var wire 1 0 force_short_oneshot $end
$var wire 1 1 isrc_sel $end
$var wire 3 6 otrip [2:0] $end
$var wire 1 % startup_timed_out $end
$var wire 1 & pwup_filt $end
$var wire 1 ' porb_h $end
$var wire 1 ( porb $end
$var wire 1 7 por_unbuf $end
$var wire 1 ) por_timed_out $end
$var wire 1 * por $end
$var wire 8 8 otrip_decoded [7:0] $end
$var wire 1 9 osc_ena $end
$var wire 1 + osc_ck_256 $end
$var wire 1 , osc_ck $end
$var wire 1 : force_pdnb $end
$var real 1 ; avdd $end
$var real 1 < ibg_200n $end
$var real 1 = vbg_1v2 $end
$var real 1 > vin $end
$var real 1 ? itest $end
$scope module por_ana $end
$var wire 1 ! avss $end
$var wire 1 " dvdd $end
$var wire 1 # dvss $end
$var wire 1 1 isrc_sel $end
$var wire 1 * por $end
$var wire 1 & pwup_filt $end
$var wire 1 ' porb_h $end
$var wire 1 ( porb $end
$var wire 1 7 por_unbuf $end
$var wire 8 @ otrip_decoded [7:0] $end
$var wire 1 9 osc_ena $end
$var wire 1 , osc_ck $end
$var wire 1 : force_pdnb $end
$var real 1 A avdd $end
$var real 1 B ibg_200n $end
$var real 1 C vbg_1v2 $end
$var real 1 D vin $end
$var real 1 E itest $end
$var real 1 F ibias $end
$scope module comparator $end
$var wire 1 ! avss $end
$var wire 1 " dvdd $end
$var wire 1 # dvss $end
$var wire 1 : ena $end
$var wire 1 & dout $end
$var real 1 G avdd $end
$var real 1 H vinn $end
$var real 1 I vinp $end
$var real 1 J ibias $end
$upscope $end
$scope module ibias_gen $end
$var wire 1 ! avss $end
$var wire 1 " dvdd $end
$var wire 1 # dvss $end
$var wire 1 1 isrc_sel $end
$var wire 1 : ena $end
$var real 1 K avdd $end
$var real 1 L ibg_200n $end
$var real 1 M itest $end
$var real 1 N ibias $end
$upscope $end
$scope module rc_osc $end
$var wire 1 " dvdd $end
$var wire 1 # dvss $end
$var wire 1 9 osc_ena $end
$var reg 1 , osc_ck $end
$upscope $end
$scope module rstring_mux $end
$var wire 1 ! avss $end
$var wire 1 " dvdd $end
$var wire 1 # dvss $end
$var wire 8 O otrip_decoded [7:0] $end
$var wire 1 : ena $end
$var real 1 P avdd $end
$var real 1 Q vin $end
$var real 1 R vtrip_7 $end
$var real 1 S vtrip_6 $end
$var real 1 T vtrip_5 $end
$var real 1 U vtrip_4 $end
$var real 1 V vtrip_3 $end
$var real 1 W vtrip_2 $end
$var real 1 X vtrip_1 $end
$var real 1 Y vtrip_0 $end
$upscope $end
$upscope $end
$scope module por_dig $end
$var wire 1 . force_pdn $end
$var wire 1 : force_pdnb $end
$var wire 1 / force_rc_osc $end
$var wire 1 0 force_short_oneshot $end
$var wire 1 , osc_ck $end
$var wire 1 9 osc_ena $end
$var wire 3 Z otrip [2:0] $end
$var wire 1 7 por_unbuf $end
$var wire 1 & pwup_filt $end
$var wire 1 % startup_timed_out $end
$var wire 1 ) por_timed_out $end
$var reg 7 [ cnt_ck_256 [6:0] $end
$var reg 15 \ cnt_por [14:0] $end
$var reg 1 ] cnt_rsb $end
$var reg 1 ^ cnt_rsb_stg1 $end
$var reg 1 _ cnt_rsb_stg2 $end
$var reg 9 ` cnt_st [8:0] $end
$var reg 1 + osc_ck_256 $end
$var reg 8 a otrip_decoded [7:0] $end
$upscope $end
$upscope $end
$upscope $end
$enddefinitions $end
$comment Show the parameter values. $end
$dumpall
$end
#0
$dumpvars
b10000000 a
b0 `
0_
0^
0]
b0 \
b0 [
b111 Z
r1 Y
r0.9714285714285714 X
r0.9428571428571428 W
r0.9142857142857143 V
r0.8857142857142857 U
r0.8571428571428571 T
r0.8285714285714286 S
r0.8 R
r0.8 Q
r2 P
b10000000 O
r7e-07 N
r0 M
r2e-07 L
r2 K
r7e-07 J
r0.8 I
r1.2 H
r2 G
r7e-07 F
r0 E
r0.8 D
r1.2 C
r2e-07 B
r2 A
b10000000 @
r0 ?
r0.8 >
r1.2 =
r2e-07 <
r2 ;
1:
09
b10000000 8
07
b111 6
r1.2 5
r2e-07 4
r2 3
b111 2
01
00
0/
0.
0-
0,
0+
0*
0)
1(
1'
0&
0%
1$
0#
1"
0!
$end
#20000000
19
1&
r1.24 >
r1.24 D
r1.24 I
r1.24 Q
r1.55 Y
r1.505714285714286 X
r1.461428571428572 W
r1.417142857142857 V
r1.372857142857143 U
r1.328571428571429 T
r1.284285714285714 S
r1.24 R
r3.1 3
r3.1 ;
r3.1 A
r3.1 G
r3.1 K
r3.1 P
#20000214
1^
1,
#20000976
0,
#20001738
1_
1,
#20002500
0,
#20003262
1]
1,
#20004024
0,
#20004786
b1 `
b1 [
1,
#20005548
0,
#20006310
b10 [
b10 `
1,
#20007072
0,
#20007834
b11 `
b11 [
1,
#20008596
0,
#20009358
b100 [
b100 `
1,
#20010120
0,
#20010882
b101 `
b101 [
1,
#20011644
0,
#20012406
b110 [
b110 `
1,
#20013168
0,
#20013930
b111 `
b111 [
1,
#20014692
0,
#20015454
b1000 [
b1000 `
1,
#20016216
0,
#20016978
b1001 `
b1001 [
1,
#20017740
0,
#20018502
b1010 [
b1010 `
1,
#20019264
0,
#20020026
b1011 `
b1011 [
1,
#20020788
0,
#20021550
b1100 [
b1100 `
1,
#20022312
0,
#20023074
b1101 `
b1101 [
1,
#20023836
0,
#20024598
b1110 [
b1110 `
1,
#20025360
0,
#20026122
b1111 `
b1111 [
1,
#20026884
0,
#20027646
b10000 [
b10000 `
1,
#20028408
0,
#20029170
b10001 `
b10001 [
1,
#20029932
0,
#20030694
b10010 [
b10010 `
1,
#20031456
0,
#20032218
b10011 `
b10011 [
1,
#20032980
0,
#20033742
b10100 [
b10100 `
1,
#20034504
0,
#20035266
b10101 `
b10101 [
1,
#20036028
0,
#20036790
b10110 [
b10110 `
1,
#20037552
0,
#20038314
b10111 `
b10111 [
1,
#20039076
0,
#20039838
b11000 [
b11000 `
1,
#20040600
0,
#20041362
b11001 `
b11001 [
1,
#20042124
0,
#20042886
b11010 [
b11010 `
1,
#20043648
0,
#20044410
b11011 `
b11011 [
1,
#20045172
0,
#20045934
b11100 [
b11100 `
1,
#20046696
0,
#20047458
b11101 `
b11101 [
1,
#20048220
0,
#20048982
b11110 [
b11110 `
1,
#20049744
0,
#20050506
b11111 `
b11111 [
1,
#20051268
0,
#20052030
b100000 [
b100000 `
1,
#20052792
0,
#20053554
b100001 `
b100001 [
1,
#20054316
0,
#20055078
b100010 [
b100010 `
1,
#20055840
0,
#20056602
b100011 `
b100011 [
1,
#20057364
0,
#20058126
b100100 [
b100100 `
1,
#20058888
0,
#20059650
b100101 `
b100101 [
1,
#20060412
0,
#20061174
b100110 [
b100110 `
1,
#20061936
0,
#20062698
b100111 `
b100111 [
1,
#20063460
0,
#20064222
b101000 [
b101000 `
1,
#20064984
0,
#20065746
b101001 `
b101001 [
1,
#20066508
0,
#20067270
b101010 [
b101010 `
1,
#20068032
0,
#20068794
b101011 `
b101011 [
1,
#20069556
0,
#20070318
b101100 [
b101100 `
1,
#20071080
0,
#20071842
b101101 `
b101101 [
1,
#20072604
0,
#20073366
b101110 [
b101110 `
1,
#20074128
0,
#20074890
b101111 `
b101111 [
1,
#20075652
0,
#20076414
b110000 [
b110000 `
1,
#20077176
0,
#20077938
b110001 `
b110001 [
1,
#20078700
0,
#20079462
b110010 [
b110010 `
1,
#20080224
0,
#20080986
b110011 `
b110011 [
1,
#20081748
0,
#20082510
b110100 [
b110100 `
1,
#20083272
0,
#20084034
b110101 `
b110101 [
1,
#20084796
0,
#20085558
b110110 [
b110110 `
1,
#20086320
0,
#20087082
b110111 `
b110111 [
1,
#20087844
0,
#20088606
b111000 [
b111000 `
1,
#20089368
0,
#20090130
b111001 `
b111001 [
1,
#20090892
0,
#20091654
b111010 [
b111010 `
1,
#20092416
0,
#20093178
b111011 `
b111011 [
1,
#20093940
0,
#20094702
b111100 [
b111100 `
1,
#20095464
0,
#20096226
b111101 `
b111101 [
1,
#20096988
0,
#20097750
b111110 [
b111110 `
1,
#20098512
0,
#20099274
b111111 `
b111111 [
1,
#20100036
0,
#20100798
b1000000 [
b1000000 `
1,
#20101560
0,
#20102322
b1000001 `
b1000001 [
1,
#20103084
0,
#20103846
b1000010 [
b1000010 `
1,
#20104608
0,
#20105370
b1000011 `
b1000011 [
1,
#20106132
0,
#20106894
b1000100 [
b1000100 `
1,
#20107656
0,
#20108418
b1000101 `
b1000101 [
1,
#20109180
0,
#20109942
b1000110 [
b1000110 `
1,
#20110704
0,
#20111466
b1000111 `
b1000111 [
1,
#20112228
0,
#20112990
b1001000 [
b1001000 `
1,
#20113752
0,
#20114514
b1001001 `
b1001001 [
1,
#20115276
0,
#20116038
b1001010 [
b1001010 `
1,
#20116800
0,
#20117562
b1001011 `
b1001011 [
1,
#20118324
0,
#20119086
b1001100 [
b1001100 `
1,
#20119848
0,
#20120610
b1001101 `
b1001101 [
1,
#20121372
0,
#20122134
b1001110 [
b1001110 `
1,
#20122896
0,
#20123658
b1001111 `
b1001111 [
1,
#20124420
0,
#20125182
b1010000 [
b1010000 `
1,
#20125944
0,
#20126706
b1010001 `
b1010001 [
1,
#20127468
0,
#20128230
b1010010 [
b1010010 `
1,
#20128992
0,
#20129754
b1010011 `
b1010011 [
1,
#20130516
0,
#20131278
b1010100 [
b1010100 `
1,
#20132040
0,
#20132802
b1010101 `
b1010101 [
1,
#20133564
0,
#20134326
b1010110 [
b1010110 `
1,
#20135088
0,
#20135850
b1010111 `
b1010111 [
1,
#20136612
0,
#20137374
b1011000 [
b1011000 `
1,
#20138136
0,
#20138898
b1011001 `
b1011001 [
1,
#20139660
0,
#20140422
b1011010 [
b1011010 `
1,
#20141184
0,
#20141946
b1011011 `
b1011011 [
1,
#20142708
0,
#20143470
b1011100 [
b1011100 `
1,
#20144232
0,
#20144994
b1011101 `
b1011101 [
1,
#20145756
0,
#20146518
b1011110 [
b1011110 `
1,
#20147280
0,
#20148042
b1011111 `
b1011111 [
1,
#20148804
0,
#20149566
b1100000 [
b1100000 `
1,
#20150328
0,
#20151090
b1100001 `
b1100001 [
1,
#20151852
0,
#20152614
b1100010 [
b1100010 `
1,
#20153376
0,
#20154138
b1100011 `
b1100011 [
1,
#20154900
0,
#20155662
b1100100 [
b1100100 `
1,
#20156424
0,
#20157186
b1100101 `
b1100101 [
1,
#20157948
0,
#20158710
b1100110 [
b1100110 `
1,
#20159472
0,
#20160234
b1100111 `
b1100111 [
1,
#20160996
0,
#20161758
b1101000 [
b1101000 `
1,
#20162520
0,
#20163282
b1101001 `
b1101001 [
1,
#20164044
0,
#20164806
b1101010 [
b1101010 `
1,
#20165568
0,
#20166330
b1101011 `
b1101011 [
1,
#20167092
0,
#20167854
b1101100 [
b1101100 `
1,
#20168616
0,
#20169378
b1101101 `
b1101101 [
1,
#20170140
0,
#20170902
b1101110 [
b1101110 `
1,
#20171664
0,
#20172426
b1101111 `
b1101111 [
1,
#20173188
0,
#20173950
b1110000 [
b1110000 `
1,
#20174712
0,
#20175474
b1110001 `
b1110001 [
1,
#20176236
0,
#20176998
b1110010 [
b1110010 `
1,
#20177760
0,
#20178522
b1110011 `
b1110011 [
1,
#20179284
0,
#20180046
b1110100 [
b1110100 `
1,
#20180808
0,
#20181570
b1110101 `
b1110101 [
1,
#20182332
0,
#20183094
b1110110 [
b1110110 `
1,
#20183856
0,
#20184618
b1110111 `
b1110111 [
1,
#20185380
0,
#20186142
b1111000 [
b1111000 `
1,
#20186904
0,
#20187666
b1111001 `
b1111001 [
1,
#20188428
0,
#20189190
b1111010 [
b1111010 `
1,
#20189952
0,
#20190714
b1111011 `
b1111011 [
1,
#20191476
0,
#20192238
b1111100 [
b1111100 `
1,
#20193000
0,
#20193762
b1111101 `
b1111101 [
1,
#20194524
0,
#20195286
b1111110 [
b1111110 `
1,
#20196048
0,
#20196810
b1111111 `
b1111111 [
1,
#20197572
0,
#20198334
1+
b0 [
b10000000 `
1,
#20199096
0,
#20199858
b10000001 `
b1 [
1,
#20200620
0,
#20201382
b10 [
b10000010 `
1,
#20202144
0,
#20202906
b10000011 `
b11 [
1,
#20203668
0,
#20204430
b100 [
b10000100 `
1,
#20205192
0,
#20205954
b10000101 `
b101 [
1,
#20206716
0,
#20207478
b110 [
b10000110 `
1,
#20208240
0,
#20209002
b10000111 `
b111 [
1,
#20209764
0,
#20210526
b1000 [
b10001000 `
1,
#20211288
0,
#20212050
b10001001 `
b1001 [
1,
#20212812
0,
#20213574
b1010 [
b10001010 `
1,
#20214336
0,
#20215098
b10001011 `
b1011 [
1,
#20215860
0,
#20216622
b1100 [
b10001100 `
1,
#20217384
0,
#20218146
b10001101 `
b1101 [
1,
#20218908
0,
#20219670
b1110 [
b10001110 `
1,
#20220432
0,
#20221194
b10001111 `
b1111 [
1,
#20221956
0,
#20222718
b10000 [
b10010000 `
1,
#20223480
0,
#20224242
b10010001 `
b10001 [
1,
#20225004
0,
#20225766
b10010 [
b10010010 `
1,
#20226528
0,
#20227290
b10010011 `
b10011 [
1,
#20228052
0,
#20228814
b10100 [
b10010100 `
1,
#20229576
0,
#20230338
b10010101 `
b10101 [
1,
#20231100
0,
#20231862
b10110 [
b10010110 `
1,
#20232624
0,
#20233386
b10010111 `
b10111 [
1,
#20234148
0,
#20234910
b11000 [
b10011000 `
1,
#20235672
0,
#20236434
b10011001 `
b11001 [
1,
#20237196
0,
#20237958
b11010 [
b10011010 `
1,
#20238720
0,
#20239482
b10011011 `
b11011 [
1,
#20240244
0,
#20241006
b11100 [
b10011100 `
1,
#20241768
0,
#20242530
b10011101 `
b11101 [
1,
#20243292
0,
#20244054
b11110 [
b10011110 `
1,
#20244816
0,
#20245578
b10011111 `
b11111 [
1,
#20246340
0,
#20247102
b100000 [
b10100000 `
1,
#20247864
0,
#20248626
b10100001 `
b100001 [
1,
#20249388
0,
#20250150
b100010 [
b10100010 `
1,
#20250912
0,
#20251674
b10100011 `
b100011 [
1,
#20252436
0,
#20253198
b100100 [
b10100100 `
1,
#20253960
0,
#20254722
b10100101 `
b100101 [
1,
#20255484
0,
#20256246
b100110 [
b10100110 `
1,
#20257008
0,
#20257770
b10100111 `
b100111 [
1,
#20258532
0,
#20259294
b101000 [
b10101000 `
1,
#20260056
0,
#20260818
b10101001 `
b101001 [
1,
#20261580
0,
#20262342
b101010 [
b10101010 `
1,
#20263104
0,
#20263866
b10101011 `
b101011 [
1,
#20264628
0,
#20265390
b101100 [
b10101100 `
1,
#20266152
0,
#20266914
b10101101 `
b101101 [
1,
#20267676
0,
#20268438
b101110 [
b10101110 `
1,
#20269200
0,
#20269962
b10101111 `
b101111 [
1,
#20270724
0,
#20271486
b110000 [
b10110000 `
1,
#20272248
0,
#20273010
b10110001 `
b110001 [
1,
#20273772
0,
#20274534
b110010 [
b10110010 `
1,
#20275296
0,
#20276058
b10110011 `
b110011 [
1,
#20276820
0,
#20277582
b110100 [
b10110100 `
1,
#20278344
0,
#20279106
b10110101 `
b110101 [
1,
#20279868
0,
#20280630
b110110 [
b10110110 `
1,
#20281392
0,
#20282154
b10110111 `
b110111 [
1,
#20282916
0,
#20283678
b111000 [
b10111000 `
1,
#20284440
0,
#20285202
b10111001 `
b111001 [
1,
#20285964
0,
#20286726
b111010 [
b10111010 `
1,
#20287488
0,
#20288250
b10111011 `
b111011 [
1,
#20289012
0,
#20289774
b111100 [
b10111100 `
1,
#20290536
0,
#20291298
b10111101 `
b111101 [
1,
#20292060
0,
#20292822
b111110 [
b10111110 `
1,
#20293584
0,
#20294346
b10111111 `
b111111 [
1,
#20295108
0,
#20295870
b1000000 [
b11000000 `
1,
#20296632
0,
#20297394
b11000001 `
b1000001 [
1,
#20298156
0,
#20298918
b1000010 [
b11000010 `
1,
#20299680
0,
#20300442
b11000011 `
b1000011 [
1,
#20301204
0,
#20301966
b1000100 [
b11000100 `
1,
#20302728
0,
#20303490
b11000101 `
b1000101 [
1,
#20304252
0,
#20305014
b1000110 [
b11000110 `
1,
#20305776
0,
#20306538
b11000111 `
b1000111 [
1,
#20307300
0,
#20308062
b1001000 [
b11001000 `
1,
#20308824
0,
#20309586
b11001001 `
b1001001 [
1,
#20310348
0,
#20311110
b1001010 [
b11001010 `
1,
#20311872
0,
#20312634
b11001011 `
b1001011 [
1,
#20313396
0,
#20314158
b1001100 [
b11001100 `
1,
#20314920
0,
#20315682
b11001101 `
b1001101 [
1,
#20316444
0,
#20317206
b1001110 [
b11001110 `
1,
#20317968
0,
#20318730
b11001111 `
b1001111 [
1,
#20319492
0,
#20320254
b1010000 [
b11010000 `
1,
#20321016
0,
#20321778
b11010001 `
b1010001 [
1,
#20322540
0,
#20323302
b1010010 [
b11010010 `
1,
#20324064
0,
#20324826
b11010011 `
b1010011 [
1,
#20325588
0,
#20326350
b1010100 [
b11010100 `
1,
#20327112
0,
#20327874
b11010101 `
b1010101 [
1,
#20328636
0,
#20329398
b1010110 [
b11010110 `
1,
#20330160
0,
#20330922
b11010111 `
b1010111 [
1,
#20331684
0,
#20332446
b1011000 [
b11011000 `
1,
#20333208
0,
#20333970
b11011001 `
b1011001 [
1,
#20334732
0,
#20335494
b1011010 [
b11011010 `
1,
#20336256
0,
#20337018
b11011011 `
b1011011 [
1,
#20337780
0,
#20338542
b1011100 [
b11011100 `
1,
#20339304
0,
#20340066
b11011101 `
b1011101 [
1,
#20340828
0,
#20341590
b1011110 [
b11011110 `
1,
#20342352
0,
#20343114
b11011111 `
b1011111 [
1,
#20343876
0,
#20344638
b1100000 [
b11100000 `
1,
#20345400
0,
#20346162
b11100001 `
b1100001 [
1,
#20346924
0,
#20347686
b1100010 [
b11100010 `
1,
#20348448
0,
#20349210
b11100011 `
b1100011 [
1,
#20349972
0,
#20350734
b1100100 [
b11100100 `
1,
#20351496
0,
#20352258
b11100101 `
b1100101 [
1,
#20353020
0,
#20353782
b1100110 [
b11100110 `
1,
#20354544
0,
#20355306
b11100111 `
b1100111 [
1,
#20356068
0,
#20356830
b1101000 [
b11101000 `
1,
#20357592
0,
#20358354
b11101001 `
b1101001 [
1,
#20359116
0,
#20359878
b1101010 [
b11101010 `
1,
#20360640
0,
#20361402
b11101011 `
b1101011 [
1,
#20362164
0,
#20362926
b1101100 [
b11101100 `
1,
#20363688
0,
#20364450
b11101101 `
b1101101 [
1,
#20365212
0,
#20365974
b1101110 [
b11101110 `
1,
#20366736
0,
#20367498
b11101111 `
b1101111 [
1,
#20368260
0,
#20369022
b1110000 [
b11110000 `
1,
#20369784
0,
#20370546
b11110001 `
b1110001 [
1,
#20371308
0,
