verilog/por_dig.v
module por_dig(
//INPUTS
input logic [2:0] otrip,
input logic force_pdn,
input logic force_rc_osc,
input logic force_short_oneshot,
input logic pwup_filt,
input logic osc_ck,
//OUTPUTS
output osc_ena,
output logic [7:0] otrip_decoded,
output force_pdnb,
output por_unbuf,
//DEBUG OUTPUTS
output startup_timed_out,
output por_timed_out
);

  assign force_pdnb = ~force_pdn;
  assign osc_ena = force_rc_osc | (pwup_filt & ~por_timed_out);

  //TRIP-VOLTAGE 3-to-8 DECODER
  always @ (otrip) begin
    case(otrip)
      3'b111: otrip_decoded = 8'b10000000;
      3'b110: otrip_decoded = 8'b01000000;
      3'b101: otrip_decoded = 8'b00100000;
      3'b100: otrip_decoded = 8'b00010000;
      3'b011: otrip_decoded = 8'b00001000;
      3'b010: otrip_decoded = 8'b00000100;
      3'b001: otrip_decoded = 8'b00000010;
      3'b000: otrip_decoded = 8'b00000001;
    endcase
  end

  //COUNTER RESET
  reg cnt_rsb_stg1, cnt_rsb_stg2, cnt_rsb;

  always @ (posedge osc_ck or negedge pwup_filt) begin
    if (!pwup_filt) begin
      cnt_rsb_stg1 <= 0;
      cnt_rsb_stg2 <= 0;
      cnt_rsb <= 0;
    end else begin
      cnt_rsb_stg1 <= 1;
      cnt_rsb_stg2 <= cnt_rsb_stg1;
      cnt_rsb <= cnt_rsb_stg2;
    end
  end

  //9-BIT STARTUP ONE-SHOT
  reg [4:0] cnt_st;

  assign startup_timed_out = (cnt_st == 5'b11111);

  always @ (posedge osc_ck or negedge cnt_rsb) begin
    if (!cnt_rsb) begin
      cnt_st <= 0;
    end else begin
      cnt_st <= startup_timed_out ? cnt_st : force_short_oneshot ? (cnt_st & 5'b11110) + 5'b00011 : cnt_st + 1;
    end
  end

  //OUTPUT
  assign por_unbuf = startup_timed_out & (!por_timed_out);

  //15-BIT POR ONE-SHOT
  reg [10:0] cnt_por;

  assign por_timed_out = (cnt_por == 11'b11111111111);

  always @ (posedge osc_ck or negedge cnt_rsb) begin
    if (!cnt_rsb) begin
      cnt_por <= 0;
    end else begin
      cnt_por <= por_unbuf ? force_short_oneshot ? (cnt_por & 11'b11111100000) + 11'b00000111111 : cnt_por + 1 : cnt_por;
    end
  end

endmodule

verilog/behavioral/rc_osc.v
//`timescale 1ns/100fs

module rc_osc(
input logic osc_ena,
input logic dvdd,
input logic dvss,
output logic osc_ck
);

//656kHz
always #12195.2 osc_ck = osc_ena ? ~osc_ck : 0;

initial begin
  osc_ck <= 0;
end
endmodule

verilog/behavioral/comparator.v
module comparator(
input real avdd,
input logic avss,
input logic dvdd,
input logic dvss,
input real vinp,
input real vinn,
input logic ena,
input real ibias,
output dout
);

assign dout = ena & (ibias > 200e-9) ? (vinp > vinn) ? 1 : 0 : 0;

endmodule

verilog/behavioral/ibias_gen.v
module ibias_gen(
input real avdd,
input logic avss,
input logic dvdd,
input logic dvss,
input logic ena,
input logic isrc_sel,
input real ibg_200n,
output real ibias,
output real itest
);

assign ibias = ena ? isrc_sel ? 800e-9 : 700e-9 : 0;

endmodule

verilog/behavioral/rstring_mux.v
//############################################################################
// Copyright 2024 Ajacci, Ltd. Co.
// License: Apache License, Version 2.0 with Addendum, see NOTICE
// Date: 22 March, 2024   Rev 0
// Description: Resistor string with analog mux model
//############################################################################

module rstring_mux(
//INPUT
input real avdd,
input logic avss,
input logic dvdd,
input logic dvss,
input logic ena,
input logic [7:0] otrip_decoded,
//OUTPUTS
output real vin
);

`define UNIT_R 50e3

real vtrip_7;
real vtrip_6;
real vtrip_5;
real vtrip_4;
real vtrip_3;
real vtrip_2;
real vtrip_1;
real vtrip_0;

assign vtrip_0 = ena ? avdd * (`UNIT_R*7 + `UNIT_R*28) / (`UNIT_R*70) : avdd;
assign vtrip_1 = ena ? avdd * (`UNIT_R*6 + `UNIT_R*28) / (`UNIT_R*70) : avdd;
assign vtrip_2 = ena ? avdd * (`UNIT_R*5 + `UNIT_R*28) / (`UNIT_R*70) : avdd;
assign vtrip_3 = ena ? avdd * (`UNIT_R*4 + `UNIT_R*28) / (`UNIT_R*70) : avdd;
assign vtrip_4 = ena ? avdd * (`UNIT_R*3 + `UNIT_R*28) / (`UNIT_R*70) : avdd;
assign vtrip_5 = ena ? avdd * (`UNIT_R*2 + `UNIT_R*28) / (`UNIT_R*70) : avdd;
assign vtrip_6 = ena ? avdd * (`UNIT_R*1 + `UNIT_R*28) / (`UNIT_R*70) : avdd;
assign vtrip_7 = ena ? avdd * (`UNIT_R*0 + `UNIT_R*28) / (`UNIT_R*70) : avdd;

  always @ (vtrip_7, vtrip_6, vtrip_5, vtrip_4, vtrip_3, vtrip_2, vtrip_1, vtrip_0, otrip_decoded) begin
    case (otrip_decoded)
      8'b10000000: vin = vtrip_7;
      8'b01000000: vin = vtrip_6;
      8'b00100000: vin = vtrip_5;
      8'b00010000: vin = vtrip_4;
      8'b00001000: vin = vtrip_3;
      8'b00000100: vin = vtrip_2;
      8'b00000010: vin = vtrip_1;
      8'b00000001: vin = vtrip_0;
      default: vin = 0;
    endcase
  end

endmodule

verilog/por_ana.v
//############################################################################
// Copyright 2024 Ajacci, Ltd. Co.
// License: Apache License, Version 2.0 with Addendum, see NOTICE
// Date: 22 March, 2024   Rev 0
// Description: Power-on-reset analog model
//############################################################################

module por_ana(
//INPUTS
input real avdd,
input logic avss,
input logic dvdd,
input logic dvss,
input logic [7:0] otrip_decoded,
input real vbg_1v2,
input logic force_pdnb,
input logic isrc_sel,
input real ibg_200n,
input logic osc_ena,
input logic por_unbuf,
//OUTPUTS
output pwup_filt,
output osc_ck,
output logic por,
output logic porb,
output logic porb_h,
output real vin,
output real itest
);

assign por = por_unbuf; //lvls to avdd
assign porb = !por_unbuf; //lvls to avdd
assign porb_h = !por_unbuf; //lvls to avdd

rstring_mux rstring_mux(
.avdd(avdd),
.avss(avss),
.dvdd(dvdd),
.dvss(dvss),
.ena(force_pdnb),
.otrip_decoded(otrip_decoded), //lvls not modeled
.vin(vin)
);

real ibias;

ibias_gen ibias_gen(
.avdd(avdd),
.avss(avss),
.dvdd(dvdd),
.dvss(dvss),
.ena(force_pdnb),
.isrc_sel(isrc_sel),
.ibg_200n(ibg_200n),
.ibias(ibias),
.itest(itest)
);

comparator comparator(
.avdd(avdd),
.avss(avss),
.dvdd(dvdd),
.dvss(dvss),
.vinp(vin),
.vinn(vbg_1v2),
.ena(force_pdnb),
.ibias(ibias),
.dout(pwup_filt)
);

rc_osc rc_osc(
.dvdd(dvdd),
.dvss(dvss),
.osc_ena(osc_ena),
.osc_ck(osc_ck)
);

endmodule

verilog/por.v
`include "behavioral/rc_osc.v"
`include "behavioral/rstring_mux.v"
`include "behavioral/comparator.v"
`include "behavioral/ibias_gen.v"
`include "por_ana.v"
`include "por_dig.v"

module por(
//INPUTS
input real avdd,
input logic avss,
input logic dvdd,
input logic dvss,
input real vbg_1v2,
input logic [2:0] otrip, //trip voltage select
input logic force_pdn, //a 1 means power down the block
input logic force_rc_osc, //force rc oscillator on
input logic force_short_oneshot, //shorten 1ms/50ms timer for faster simulation
input logic isrc_sel, //chooses between internal bias gen (0) or external bandgap current (1)
input real ibg_200n, //bandgap current
//OUTPUTS
output porb_h, //negative logic por 3v3
output porb, //negative logic por 1v8
output por, //positive logic por 1v8
//DEBUG OUTPUTS
output osc_ck, //~656kHz, main clock
output real itest, //700nA bias current
output pwup_filt, //high when avdd > trip point
output real vin, //avdd divided down voltage to compare to 1.2V bg
output startup_timed_out, //initial 1ms timer
output por_timed_out //50ms timer
);

wire [7:0] otrip_decoded;

por_ana por_ana(
//INPUTS
.avdd(avdd),
.avss(avss),
.dvdd(dvdd),
.dvss(dvss),
.otrip_decoded(otrip_decoded),
.vbg_1v2(vbg_1v2),
.force_pdnb(force_pdnb),
.isrc_sel(isrc_sel),
.ibg_200n(ibg_200n),
.osc_ena(osc_ena),
.por_unbuf(por_unbuf),
//OUTPUTS
.pwup_filt(pwup_filt),
.osc_ck(osc_ck),
.por(por),
.porb(porb),
.porb_h(porb_h),
//DEBUG OUTPUTS
.vin(vin), //input to comparator for comparing to 1.2V bg voltage
.itest(itest) //mirror of current gen 0.7uA nominal
);

por_dig por_dig(
//INPUTS
.otrip(otrip),
.force_pdn(force_pdn),
.force_rc_osc(force_rc_osc),
.force_short_oneshot(force_short_oneshot),
.pwup_filt(pwup_filt),
.osc_ck(osc_ck),
//OUTPUTS
.osc_ena(osc_ena),
.otrip_decoded(otrip_decoded),
.force_pdnb(force_pdnb),
.por_unbuf(por_unbuf),
//DEBUG OUTPUTS
.startup_timed_out(startup_timed_out),
.por_timed_out(por_timed_out)
);

endmodule

verilog/tb_por.v
`include "por.v"
module tb_por();

real avdd;
real vbg_1v2;
logic [2:0] otrip;
logic force_pdn;
logic force_rc_osc;
logic force_short_oneshot;
logic isrc_sel;
real ibg_200n;

por por(
//INPUTS
.avdd(avdd),
.avss(avss),
.dvdd(dvdd),
.dvss(dvss),
.vbg_1v2(vbg_1v2),
.otrip(otrip),
.force_pdn(force_pdn), //debug
.force_rc_osc(force_rc_osc), //debug
.force_short_oneshot(force_short_oneshot), //debug, fast sim
.isrc_sel(isrc_sel), //debug
.ibg_200n(ibg_200n), //debug 200nA current
//OUTPUTS
.porb_h(porb_h),
.porb(porb),
.por(por),
//DEBUG OUTPUTS
.osc_ck(osc_ck),
.itest(itest),
.pwup_filt(pwup_filt),
.vin(vin),
.startup_timed_out(startup_timed_out),
.por_timed_out(por_timed_out)
);

assign avss = 1'b0;
assign dvdd = 1'b1;
assign dvss = 1'b0;

initial begin
  $dumpfile("tb_por.vcd");
  $dumpvars(0,tb_por);

  //INPUTS
  avdd = 2.0;
  vbg_1v2 = 1.2;
  otrip = 3'b000;
  //DEBUG INPUTS
  force_pdn = 1'b0;
  force_rc_osc = 1'b0;
  force_short_oneshot = 1'b1;
  isrc_sel = 1'b0;
  ibg_200n = 200e-9;
  #20000000
  avdd = 3.1;
  #80000000
  avdd = 2.0;
  #40000000
  avdd = 3.1;
  #80000000
  $finish;
end


endmodule

verilog/tb_por.vcd
$date
	Sun Mar 17 23:05:05 2024
$end
$version
	Icarus Verilog
$end
$timescale
	1s
$end
$scope module tb_por $end
$var wire 1 ! avss $end
$var wire 1 " dvdd $end
$var wire 1 # dvss $end
$var wire 1 $ vin $end
$var wire 1 % startup_timed_out $end
$var wire 1 & pwup_filt $end
$var wire 1 ' porb_h $end
$var wire 1 ( porb $end
$var wire 1 ) por_timed_out $end
$var wire 1 * por $end
$var wire 1 + osc_ck $end
$var wire 1 , itest $end
$var reg 1 - force_pdn $end
$var reg 1 . force_rc_osc $end
$var reg 1 / force_short_oneshot $end
$var reg 1 0 isrc_sel $end
$var reg 3 1 otrip [2:0] $end
$var real 1 2 avdd $end
$var real 1 3 ibg_200n $end
$var real 1 4 vbg_1v2 $end
$scope module por $end
$var wire 1 ! avss $end
$var wire 1 " dvdd $end
$var wire 1 # dvss $end
$var wire 1 - force_pdn $end
$var wire 1 . force_rc_osc $end
$var wire 1 / force_short_oneshot $end
$var wire 1 0 isrc_sel $end
$var wire 3 5 otrip [2:0] $end
$var wire 1 % startup_timed_out $end
$var wire 1 & pwup_filt $end
$var wire 1 ' porb_h $end
$var wire 1 ( porb $end
$var wire 1 6 por_unbuf $end
$var wire 1 ) por_timed_out $end
$var wire 1 * por $end
$var wire 8 7 otrip_decoded [7:0] $end
$var wire 1 8 osc_ena $end
$var wire 1 + osc_ck $end
$var wire 1 9 force_pdnb $end
$var real 1 : avdd $end
$var real 1 ; ibg_200n $end
$var real 1 < vbg_1v2 $end
$var real 1 = vin $end
$var real 1 > itest $end
$scope module por_ana $end
$var wire 1 ! avss $end
$var wire 1 " dvdd $end
$var wire 1 # dvss $end
$var wire 1 0 isrc_sel $end
$var wire 1 * por $end
$var wire 1 & pwup_filt $end
$var wire 1 ' porb_h $end
$var wire 1 ( porb $end
$var wire 1 6 por_unbuf $end
$var wire 8 ? otrip_decoded [7:0] $end
$var wire 1 8 osc_ena $end
$var wire 1 + osc_ck $end
$var wire 1 9 force_pdnb $end
$var real 1 @ avdd $end
$var real 1 A ibg_200n $end
$var real 1 B vbg_1v2 $end
$var real 1 C vin $end
$var real 1 D itest $end
$var real 1 E ibias $end
$scope module comparator $end
$var wire 1 ! avss $end
$var wire 1 " dvdd $end
$var wire 1 # dvss $end
$var wire 1 9 ena $end
$var wire 1 & dout $end
$var real 1 F avdd $end
$var real 1 G vinn $end
$var real 1 H vinp $end
$var real 1 I ibias $end
$upscope $end
$scope module ibias_gen $end
$var wire 1 ! avss $end
$var wire 1 " dvdd $end
$var wire 1 # dvss $end
$var wire 1 0 isrc_sel $end
$var wire 1 9 ena $end
$var real 1 J avdd $end
$var real 1 K ibg_200n $end
$var real 1 L itest $end
$var real 1 M ibias $end
$upscope $end
$scope module rc_osc $end
$var wire 1 " dvdd $end
$var wire 1 # dvss $end
$var wire 1 8 osc_ena $end
$var reg 1 + osc_ck $end
$upscope $end
$scope module rstring_mux $end
$var wire 1 ! avss $end
$var wire 1 " dvdd $end
$var wire 1 # dvss $end
$var wire 8 N otrip_decoded [7:0] $end
$var wire 1 9 ena $end
$var real 1 O avdd $end
$var real 1 P vin $end
$var real 1 Q vtrip_7 $end
$var real 1 R vtrip_6 $end
$var real 1 S vtrip_5 $end
$var real 1 T vtrip_4 $end
$var real 1 U vtrip_3 $end
$var real 1 V vtrip_2 $end
$var real 1 W vtrip_1 $end
$var real 1 X vtrip_0 $end
$upscope $end
$upscope $end
$scope module por_dig $end
$var wire 1 - force_pdn $end
$var wire 1 9 force_pdnb $end
$var wire 1 . force_rc_osc $end
$var wire 1 / force_short_oneshot $end
$var wire 1 + osc_ck $end
$var wire 1 8 osc_ena $end
$var wire 3 Y otrip [2:0] $end
$var wire 1 6 por_unbuf $end
$var wire 1 & pwup_filt $end
$var wire 1 % startup_timed_out $end
$var wire 1 ) por_timed_out $end
$var reg 11 Z cnt_por [10:0] $end
$var reg 1 [ cnt_rsb $end
$var reg 1 \ cnt_rsb_stg1 $end
$var reg 1 ] cnt_rsb_stg2 $end
$var reg 5 ^ cnt_st [4:0] $end
$var reg 8 _ otrip_decoded [7:0] $end
$upscope $end
$upscope $end
$upscope $end
$enddefinitions $end
$comment Show the parameter values. $end
$dumpall
$end
#0
$dumpvars
b1 _
b0 ^
0]
0\
0[
b0 Z
b0 Y
r1 X
r0.9714285714285714 W
r0.9428571428571428 V
r0.9142857142857143 U
r0.8857142857142857 T
r0.8571428571428571 S
r0.8285714285714286 R
r0.8 Q
r1 P
r2 O
b1 N
r7e-07 M
r0 L
r2e-07 K
r2 J
r7e-07 I
r1 H
r1.2 G
r2 F
r7e-07 E
r0 D
r1 C
r1.2 B
r2e-07 A
r2 @
b1 ?
r0 >
r1 =
r1.2 <
r2e-07 ;
r2 :
19
08
b1 7
06
b0 5
r1.2 4
r2e-07 3
r2 2
b0 1
00
1/
0.
0-
0,
0+
0*
0)
1(
1'
0&
0%
1$
0#
1"
0!
$end
#20000000
18
1&
0$
r1.55 =
r1.55 C
r1.55 H
r1.55 P
r1.55 X
r1.505714285714286 W
r1.461428571428572 V
r1.417142857142857 U
r1.372857142857143 T
r1.328571428571429 S
r1.284285714285714 R
r1.24 Q
r3.1 2
r3.1 :
r3.1 @
r3.1 F
r3.1 J
r3.1 O
#20011995
1\
1+
#20024190
0+
#20036385
1]
1+
#20048580
0+
#20060775
1[
1+
#20072970
0+
#20085165
b11 ^
1+
#20097360
0+
#20109555
b101 ^
1+
#20121750
0+
#20133945
b111 ^
1+
#20146140
0+
#20158335
b1001 ^
1+
#20170530
0+
#20182725
b1011 ^
1+
#20194920
0+
#20207115
b1101 ^
1+
#20219310
0+
#20231505
b1111 ^
1+
#20243700
0+
#20255895
b10001 ^
1+
#20268090
0+
#20280285
b10011 ^
1+
#20292480
0+
#20304675
b10101 ^
1+
#20316870
0+
#20329065
b10111 ^
1+
#20341260
0+
#20353455
b11001 ^
1+
#20365650
0+
#20377845
b11011 ^
1+
#20390040
0+
#20402235
b11101 ^
1+
#20414430
0+
#20426625
0'
0(
1*
16
1%
b11111 ^
1+
#20438820
0+
#20451015
b111111 Z
1+
#20463210
0+
#20475405
b1011111 Z
1+
#20487600
0+
#20499795
b1111111 Z
1+
#20511990
0+
#20524185
b10011111 Z
1+
#20536380
0+
#20548575
b10111111 Z
1+
#20560770
0+
#20572965
b11011111 Z
1+
#20585160
0+
#20597355
b11111111 Z
1+
#20609550
0+
#20621745
b100011111 Z
1+
#20633940
0+
#20646135
b100111111 Z
1+
#20658330
0+
#20670525
b101011111 Z
1+
#20682720
0+
#20694915
b101111111 Z
1+
#20707110
0+
#20719305
b110011111 Z
1+
#20731500
0+
#20743695
b110111111 Z
1+
#20755890
0+
#20768085
b111011111 Z
1+
#20780280
0+
#20792475
b111111111 Z
1+
#20804670
0+
#20816865
b1000011111 Z
1+
#20829060
0+
#20841255
b1000111111 Z
1+
#20853450
0+
#20865645
b1001011111 Z
1+
#20877840
0+
#20890035
b1001111111 Z
1+
#20902230
0+
#20914425
b1010011111 Z
1+
#20926620
0+
#20938815
b1010111111 Z
1+
#20951010
0+
#20963205
b1011011111 Z
1+
#20975400
0+
#20987595
b1011111111 Z
1+
#20999790
0+
#21011985
b1100011111 Z
1+
#21024180
0+
#21036375
b1100111111 Z
1+
#21048570
0+
#21060765
b1101011111 Z
1+
#21072960
0+
#21085155
b1101111111 Z
1+
#21097350
0+
#21109545
b1110011111 Z
1+
#21121740
0+
#21133935
b1110111111 Z
1+
#21146130
0+
#21158325
b1111011111 Z
1+
#21170520
0+
#21182715
b1111111111 Z
1+
#21194910
0+
#21207105
b10000011111 Z
1+
#21219300
0+
#21231495
b10000111111 Z
1+
#21243690
0+
#21255885
b10001011111 Z
1+
#21268080
0+
#21280275
b10001111111 Z
1+
#21292470
0+
#21304665
b10010011111 Z
1+
#21316860
0+
#21329055
b10010111111 Z
1+
#21341250
0+
#21353445
b10011011111 Z
1+
#21365640
0+
#21377835
b10011111111 Z
1+
#21390030
0+
#21402225
b10100011111 Z
1+
#21414420
0+
#21426615
b10100111111 Z
1+
#21438810
0+
#21451005
b10101011111 Z
1+
#21463200
0+
#21475395
b10101111111 Z
1+
#21487590
0+
#21499785
b10110011111 Z
1+
#21511980
0+
#21524175
b10110111111 Z
1+
#21536370
0+
#21548565
b10111011111 Z
1+
#21560760
0+
#21572955
b10111111111 Z
1+
#21585150
0+
#21597345
b11000011111 Z
1+
#21609540
0+
#21621735
b11000111111 Z
1+
#21633930
0+
#21646125
b11001011111 Z
1+
#21658320
0+
#21670515
b11001111111 Z
1+
#21682710
0+
#21694905
b11010011111 Z
1+
#21707100
0+
#21719295
b11010111111 Z
1+
#21731490
0+
#21743685
b11011011111 Z
1+
#21755880
0+
#21768075
b11011111111 Z
1+
#21780270
0+
#21792465
b11100011111 Z
1+
#21804660
0+
#21816855
b11100111111 Z
1+
#21829050
0+
#21841245
b11101011111 Z
1+
#21853440
0+
#21865635
b11101111111 Z
1+
#21877830
0+
#21890025
b11110011111 Z
1+
#21902220
0+
#21914415
b11110111111 Z
1+
#21926610
0+
#21938805
b11111011111 Z
1+
#21951000
0+
#21963195
08
1'
1(
0*
06
1)
b11111111111 Z
1+
#21975390
0+
#100000000
0%
b0 ^
0)
b0 Z
0[
0]
0\
0&
1$
r1 =
r1 C
r1 H
r1 P
r1 X
r0.9714285714285714 W
r0.9428571428571428 V
r0.9142857142857143 U
r0.8857142857142857 T
r0.8571428571428571 S
r0.8285714285714286 R
r0.8 Q
r2 2
r2 :
r2 @
r2 F
r2 J
r2 O
#140000000
18
1&
0$
r1.55 =
r1.55 C
r1.55 H
r1.55 P
r1.55 X
r1.505714285714286 W
r1.461428571428572 V
r1.417142857142857 U
r1.372857142857143 T
r1.328571428571429 S
r1.284285714285714 R
r1.24 Q
r3.1 2
r3.1 :
r3.1 @
r3.1 F
r3.1 J
r3.1 O
#140010795
1\
1+
#140022990
0+
#140035185
1]
1+
#140047380
0+
#140059575
1[
1+
#140071770
0+
#140083965
b11 ^
1+
#140096160
0+
#140108355
b101 ^
1+
#140120550
0+
#140132745
b111 ^
1+
#140144940
0+
#140157135
b1001 ^
1+
#140169330
0+
#140181525
b1011 ^
1+
#140193720
0+
#140205915
b1101 ^
1+
#140218110
0+
#140230305
b1111 ^
1+
#140242500
0+
#140254695
b10001 ^
1+
#140266890
0+
#140279085
b10011 ^
1+
#140291280
0+
#140303475
b10101 ^
1+
#140315670
0+
#140327865
b10111 ^
1+
#140340060
0+
#140352255
b11001 ^
1+
#140364450
0+
#140376645
b11011 ^
1+
#140388840
0+
#140401035
b11101 ^
1+
#140413230
0+
#140425425
0'
0(
1*
16
1%
b11111 ^
1+
#140437620
0+
#140449815
b111111 Z
1+
#140462010
0+
#140474205
b1011111 Z
1+
#140486400
0+
#140498595
b1111111 Z
1+
#140510790
0+
#140522985
b10011111 Z
1+
#140535180
0+
#140547375
b10111111 Z
1+
#140559570
0+
#140571765
b11011111 Z
1+
#140583960
0+
#140596155
b11111111 Z
1+
#140608350
0+
#140620545
b100011111 Z
1+
#140632740
0+
#140644935
b100111111 Z
1+
#140657130
0+
#140669325
b101011111 Z
1+
#140681520
0+
#140693715
b101111111 Z
1+
#140705910
0+
#140718105
b110011111 Z
1+
#140730300
0+
#140742495
b110111111 Z
1+
#140754690
0+
#140766885
b111011111 Z
1+
#140779080
0+
#140791275
b111111111 Z
1+
#140803470
0+
#140815665
b1000011111 Z
1+
#140827860
0+
#140840055
b1000111111 Z
1+
#140852250
0+
#140864445
b1001011111 Z
1+
#140876640
0+
#140888835
b1001111111 Z
1+
#140901030
0+
#140913225
b1010011111 Z
1+
#140925420
0+
#140937615
b1010111111 Z
1+
#140949810
0+
#140962005
b1011011111 Z
1+
#140974200
0+
#140986395
b1011111111 Z
1+
#140998590
0+
#141010785
b1100011111 Z
1+
#141022980
0+
#141035175
b1100111111 Z
1+
#141047370
0+
#141059565
b1101011111 Z
1+
#141071760
0+
#141083955
b1101111111 Z
1+
#141096150
0+
#141108345
b1110011111 Z
1+
#141120540
0+
#141132735
b1110111111 Z
1+
#141144930
0+
#141157125
b1111011111 Z
1+
#141169320
0+
#141181515
b1111111111 Z
1+
#141193710
0+
#141205905
b10000011111 Z
1+
#141218100
0+
#141230295
b10000111111 Z
1+
#141242490
0+
#141254685
b10001011111 Z
1+
#141266880
0+
#141279075
b10001111111 Z
1+
#141291270
0+
#141303465
b10010011111 Z
1+
#141315660
0+
#141327855
b10010111111 Z
1+
#141340050
0+
#141352245
b10011011111 Z
1+
#141364440
0+
#141376635
b10011111111 Z
1+
#141388830
0+
#141401025
b10100011111 Z
1+
#141413220
0+
#141425415
b10100111111 Z
1+
#141437610
0+
#141449805
b10101011111 Z
1+
#141462000
0+
#141474195
b10101111111 Z
1+
#141486390
0+
#141498585
b10110011111 Z
1+
#141510780
0+
#141522975
b10110111111 Z
1+
#141535170
0+
#141547365
b10111011111 Z
1+
#141559560
0+
#141571755
b10111111111 Z
1+
#141583950
0+
#141596145
b11000011111 Z
1+
#141608340
0+
#141620535
b11000111111 Z
1+
#141632730
0+
#141644925
b11001011111 Z
1+
#141657120
0+
#141669315
b11001111111 Z
1+
#141681510
0+
#141693705
b11010011111 Z
1+
#141705900
0+
#141718095
b11010111111 Z
1+
#141730290
0+
#141742485
b11011011111 Z
1+
#141754680
0+
#141766875
b11011111111 Z
1+
#141779070
0+
#141791265
b11100011111 Z
1+
#141803460
0+
#141815655
b11100111111 Z
1+
#141827850
0+
#141840045
b11101011111 Z
1+
#141852240
0+
#141864435
b11101111111 Z
1+
#141876630
0+
#141888825
b11110011111 Z
1+
#141901020
0+
#141913215
b11110111111 Z
1+
#141925410
0+
#141937605
b11111011111 Z
1+
#141949800
0+
#141961995
08
1'
1(
0*
06
1)
b11111111111 Z
1+
